cartography/__init__.py
cartography/_base_client.py
cartography/_client.py
cartography/_compat.py
cartography/_constants.py
cartography/_exceptions.py
cartography/_files.py
cartography/_models.py
cartography/_qs.py
cartography/_resource.py
cartography/_response.py
cartography/_streaming.py
cartography/_types.py
cartography/_version.py
cartography/py.typed
cartography/_utils/__init__.py
cartography/_utils/_compat.py
cartography/_utils/_datetime_parse.py
cartography/_utils/_json.py
cartography/_utils/_logs.py
cartography/_utils/_proxy.py
cartography/_utils/_reflection.py
cartography/_utils/_resources_proxy.py
cartography/_utils/_streams.py
cartography/_utils/_sync.py
cartography/_utils/_transform.py
cartography/_utils/_typing.py
cartography/_utils/_utils.py
cartography/lib/.keep
cartography/resources/__init__.py
cartography/resources/api_info.py
cartography/resources/crawl.py
cartography/resources/download.py
cartography/resources/health.py
cartography/resources/scrape.py
cartography/resources/workflows/__init__.py
cartography/resources/workflows/workflows.py
cartography/resources/workflows/request/__init__.py
cartography/resources/workflows/request/crawl.py
cartography/resources/workflows/request/request.py
cartography/types/__init__.py
cartography/types/api_info_retrieve_response.py
cartography/types/bulk_download_result.py
cartography/types/bulk_scrape_result.py
cartography/types/crawl_create_graph_params.py
cartography/types/crawl_create_graph_response.py
cartography/types/download_create_bulk_params.py
cartography/types/download_create_bulk_response.py
cartography/types/download_create_single_params.py
cartography/types/download_create_single_response.py
cartography/types/downloader_type.py
cartography/types/engine_type.py
cartography/types/health_check_response.py
cartography/types/scrape_engine_param.py
cartography/types/scrape_scrape_bulk_params.py
cartography/types/scrape_scrape_bulk_response.py
cartography/types/scrape_scrape_single_params.py
cartography_client-0.15.0.dist-info/METADATA
cartography_client-0.15.0.dist-info/WHEEL
cartography_client-0.15.0.dist-info/licenses/LICENSE
cartography_client-0.15.0.dist-info/RECORD
